ollama_python/__init__.py
ollama_python/endpoints/__init__.py
ollama_python/endpoints/base.py
ollama_python/endpoints/embedding.py
ollama_python/endpoints/generate.py
ollama_python/endpoints/model_management.py
ollama_python/models/__init__.py
ollama_python/models/embedding.py
ollama_python/models/generate.py
ollama_python/models/model_management.py
ollama_python-0.1.1.dist-info/LICENSE
ollama_python-0.1.1.dist-info/METADATA
ollama_python-0.1.1.dist-info/WHEEL
ollama_python-0.1.1.dist-info/RECORD
